MANIFEST.in
README
requirements.txt
setup.py
ajenti.plugin.plugins.egg-info/PKG-INFO
ajenti.plugin.plugins.egg-info/SOURCES.txt
ajenti.plugin.plugins.egg-info/dependency_links.txt
ajenti.plugin.plugins.egg-info/requires.txt
ajenti.plugin.plugins.egg-info/top_level.txt
ajenti_plugin_plugins/README.md
ajenti_plugin_plugins/__init__.py
ajenti_plugin_plugins/bower.json
ajenti_plugin_plugins/main.py
ajenti_plugin_plugins/plugin.yml
ajenti_plugin_plugins/requirements.txt
ajenti_plugin_plugins/tasks.py
ajenti_plugin_plugins/views.py
ajenti_plugin_plugins/locale/app.pot
ajenti_plugin_plugins/locale/af/LC_MESSAGES/app.js
ajenti_plugin_plugins/locale/af/LC_MESSAGES/app.po
ajenti_plugin_plugins/locale/ar/LC_MESSAGES/app.js
ajenti_plugin_plugins/locale/ar/LC_MESSAGES/app.po
ajenti_plugin_plugins/locale/be/LC_MESSAGES/app.js
ajenti_plugin_plugins/locale/be/LC_MESSAGES/app.po
ajenti_plugin_plugins/locale/bg/LC_MESSAGES/app.js
ajenti_plugin_plugins/locale/bg/LC_MESSAGES/app.po
ajenti_plugin_plugins/locale/bn/LC_MESSAGES/app.js
ajenti_plugin_plugins/locale/bn/LC_MESSAGES/app.po
ajenti_plugin_plugins/locale/bs/LC_MESSAGES/app.js
ajenti_plugin_plugins/locale/bs/LC_MESSAGES/app.po
ajenti_plugin_plugins/locale/ca/LC_MESSAGES/app.js
ajenti_plugin_plugins/locale/ca/LC_MESSAGES/app.po
ajenti_plugin_plugins/locale/cs/LC_MESSAGES/app.js
ajenti_plugin_plugins/locale/cs/LC_MESSAGES/app.po
ajenti_plugin_plugins/locale/da/LC_MESSAGES/app.js
ajenti_plugin_plugins/locale/da/LC_MESSAGES/app.po
ajenti_plugin_plugins/locale/de/LC_MESSAGES/app.js
ajenti_plugin_plugins/locale/de/LC_MESSAGES/app.po
ajenti_plugin_plugins/locale/el/LC_MESSAGES/app.js
ajenti_plugin_plugins/locale/el/LC_MESSAGES/app.po
ajenti_plugin_plugins/locale/en/LC_MESSAGES/app.po
ajenti_plugin_plugins/locale/eo/LC_MESSAGES/app.js
ajenti_plugin_plugins/locale/eo/LC_MESSAGES/app.po
ajenti_plugin_plugins/locale/es-ES/LC_MESSAGES/app.js
ajenti_plugin_plugins/locale/es-ES/LC_MESSAGES/app.po
ajenti_plugin_plugins/locale/et/LC_MESSAGES/app.js
ajenti_plugin_plugins/locale/et/LC_MESSAGES/app.po
ajenti_plugin_plugins/locale/fa/LC_MESSAGES/app.js
ajenti_plugin_plugins/locale/fa/LC_MESSAGES/app.po
ajenti_plugin_plugins/locale/fi/LC_MESSAGES/app.js
