Metadata-Version: 1.2
Name: ajenti.plugin.plugins
Version: 0.49
Summary: Plugins
Home-page: https://ajenti.org
Author: Ajenti project
Author-email: e@ajenti.org
License: UNKNOWN
Platform: UNKNOWN
Requires-Python: >=3
